accrete/__init__.py
accrete/admin.py
accrete/apps.py
accrete/channels.py
accrete/config.py
accrete/consumer.py
accrete/context_processors.py
accrete/decorator.py
accrete/fields.py
accrete/forms.py
accrete/managers.py
accrete/middleware.py
accrete/models.py
accrete/storage.py
accrete/tenant.py
accrete/tests.py
accrete/urls.py
accrete/views.py
accrete/contrib/__init__.py
accrete/contrib/country/__init__.py
accrete/contrib/country/admin.py
accrete/contrib/country/apps.py
accrete/contrib/country/models.py
accrete/contrib/country/migrations/0001_initial.py
accrete/contrib/country/migrations/0002_auto_20250219_1759.py
accrete/contrib/country/migrations/0003_alter_country_options.py
accrete/contrib/country/migrations/__init__.py
accrete/contrib/log/__init__.py
accrete/contrib/log/admin.py
accrete/contrib/log/apps.py
accrete/contrib/log/config.py
accrete/contrib/log/helper.py
accrete/contrib/log/models.py
accrete/contrib/log/queries.py
accrete/contrib/log/signals.py
accrete/contrib/log/tests.py
accrete/contrib/log/views.py
accrete/contrib/log/migrations/0001_initial.py
accrete/contrib/log/migrations/0002_log_user_alter_log_new_value_type_and_more.py
accrete/contrib/log/migrations/0003_alter_log_tenant.py
accrete/contrib/log/migrations/0004_logconfig_logconfigfield.py
accrete/contrib/log/migrations/0005_logconfig_exclude_fields_and_more.py
accrete/contrib/log/migrations/0006_remove_log_accrete_log_model_cf888c_idx_and_more.py
accrete/contrib/log/migrations/0007_alter_log_new_value_type_alter_log_old_value_type.py
accrete/contrib/log/migrations/0008_activity_log_activity.py
accrete/contrib/log/migrations/__init__.py
accrete/contrib/sequence/__init__.py
accrete/contrib/sequence/admin.py
accrete/contrib/sequence/apps.py
accrete/contrib/sequence/forms.py
accrete/contrib/sequence/models.py
accrete/contrib/sequence/queries.py
accrete/contrib/sequence/tests.py
accrete/contrib/sequence/views.py
accrete/contrib/sequence/migrations/0001_initial.py
accrete-0.0.162.dist-info/METADATA
accrete-0.0.162.dist-info/WHEEL
accrete-0.0.162.dist-info/licenses/LICENSE
accrete-0.0.162.dist-info/RECORD
