Metadata-Version: 2.4
Name: accrete
Version: 0.0.162
Summary: Django Shared Schema Multi Tenant
Author-email: Benedikt Jilek <benedikt.jilek@pm.me>
License: Copyright (c) 2025 Benedikt Jilek
License-File: LICENSE
Classifier: Environment :: Web Environment
Classifier: Framework :: Django
Classifier: Intended Audience :: Developers
Classifier: License :: OSI Approved :: MIT License
Classifier: Operating System :: OS Independent
Classifier: Programming Language :: Python :: 3
Classifier: Topic :: Internet :: WWW/HTTP
Requires-Python: >=3.10
Requires-Dist: django>=5.2
Provides-Extra: contrib
Requires-Dist: celery>=5.3.4; extra == 'contrib'
Requires-Dist: django-celery-beat; extra == 'contrib'
Requires-Dist: django-template-partials; extra == 'contrib'
Requires-Dist: sqlalchemy; extra == 'contrib'
Provides-Extra: dev
Requires-Dist: build; extra == 'dev'
Requires-Dist: pytest>=7.0; extra == 'dev'
Requires-Dist: twine>=4.0.2; extra == 'dev'
